apywrapper/__init__.py
apywrapper/_abc.py
apywrapper/_api.py
apywrapper/_path.py
apywrapper/_request.py
apywrapper/_types.py
apywrapper/_utils.py
apywrapper-0.1.12.dist-info/LICENSE
apywrapper-0.1.12.dist-info/WHEEL
apywrapper-0.1.12.dist-info/METADATA
apywrapper-0.1.12.dist-info/RECORD
