Metadata-Version: 2.1
Name: apywrapper
Version: 0.1.12
Summary: make wrapper for RESTful API
Home-page: https://github.com/sh1ma/apywrapper
License: GPL-3.0-or-later
Keywords: web,restful,api,wrapper,apywrapper
Author: sh1ma
Author-email: in9lude@gmail.com
Requires-Python: >=3.8,<4.0
Classifier: Development Status :: 3 - Alpha
Classifier: Environment :: Web Environment
Classifier: License :: OSI Approved :: GNU General Public License v3 or later (GPLv3+)
Classifier: Programming Language :: Python :: 3
Classifier: Programming Language :: Python :: 3.8
Requires-Dist: dacite (>=1.5.1,<2.0.0)
Requires-Dist: httpx (>=0.14.1,<0.15.0)
Project-URL: Repository, https://github.com/sh1ma/apywrapper
